doc/Makefile
doc/conf.py
doc/documentation.rst
doc/faq.rst
doc/index.rst
doc/install.rst
doc/requirements.txt
doc/using_bmrc.rst
doc/models/dynemo.rst
doc/models/hmm.rst
doc/models/images/dynemo-cost-function.pdf
doc/models/images/dynemo-full-model.jpeg
doc/models/images/dynemo-generative-model.jpeg
doc/models/images/hmm-cost-function.pdf
doc/models/images/hmm-fisher-kernel.pdf
doc/models/images/hmm-generative-model.png
doc/tutorials/1-1_data_loading.py
doc/tutorials/1-2_data_prepare_meg.py
doc/tutorials/1-3_data_prepare_fmri.py
doc/tutorials/1-4_data_time_delay_embedding.py
doc/tutorials/2-1_static_spectra_analysis.py
doc/tutorials/2-2_static_power_analysis.py
doc/tutorials/2-3_static_aec_analysis.py
doc/tutorials/3-1_sliding_window_analysis.py
doc/tutorials/3-2_hmm_training.py
doc/tutorials/3-3_dynemo_training.py
doc/tutorials/3-4_hmm_dynemo_get_inf_params.py
doc/tutorials/4-1_hmm_multitaper_spectra.py
doc/tutorials/4-2_hmm_plotting_meg_networks.py
doc/tutorials/4-3_hmm_summary_stats.py
doc/tutorials/4-4_hmm_fmri_dual_estimation.py
doc/tutorials/4-5_hmm_plotting_fmri_networks.py
doc/tutorials/5-1_dynemo_regression_spectra.py
doc/tutorials/5-2_dynemo_plotting_networks.py
doc/tutorials/5-3_dynemo_mixing_coefs.py
doc/tutorials/6-1_epoching_alpha.py
doc/tutorials/7-1_group_contrast.py
doc/tutorials/7-2_group_network_response.py
doc/tutorials/README.rst
envs/README.md
envs/bmrc.yml
envs/fsl.yml
envs/hbaws.yml
envs/osld-tf-cuda.yml
envs/osld-tf-macos.yml
envs/osld-tf.yml
envs/osld.yml
examples/README.md
examples/decoding/README.md
examples/decoding/get_data.py
examples/decoding/prediction_pipeline.py
examples/decoding/hmm/1_calc_hmm_features.py
examples/decoding/hmm/2_predict_continuous_value.py
examples/decoding/hmm/3_predict_class_label.py
examples/decoding/hmm/README.md
examples/decoding/static/1_calc_static_features.py
examples/decoding/static/2_predict_continuous_value.py
examples/decoding/static/3_predict_class_label.py
examples/decoding/static/README.md
osl_dynamics-2.3.1.dist-info/licenses/LICENSE
osl_dynamics-2.3.1.dist-info/METADATA
osl_dynamics-2.3.1.dist-info/WHEEL
osl_dynamics-2.3.1.dist-info/entry_points.txt
osl_dynamics-2.3.1.dist-info/top_level.txt
osl_dynamics-2.3.1.dist-info/RECORD
