Metadata-Version: 2.4
Name: osl-dynamics
Version: 2.3.1
Summary: OHBA Software Library: Dynamics Toolbox
License-Expression: Apache-2.0
Project-URL: Homepage, https://github.com/OHBA-analysis/osl-dynamics
Project-URL: Documentation, https://osl-dynamics.readthedocs.io/en/latest/
Requires-Python: >=3.8
License-File: LICENSE
Dynamic: license-file
